ai_kernel_explorer/__init__.py
ai_kernel_explorer/main.py
ai_kernel_explorer/main.tcss
ai_kernel_explorer/prompt.py
ai_kernel_explorer-0.1.5.dist-info/LICENSE
ai_kernel_explorer-0.1.5.dist-info/METADATA
ai_kernel_explorer-0.1.5.dist-info/WHEEL
ai_kernel_explorer-0.1.5.dist-info/entry_points.txt
ai_kernel_explorer-0.1.5.dist-info/RECORD
