Metadata-Version: 2.1
Name: ai-kernel-explorer
Version: 0.1.5
Summary: Explore the Linux kernel source code with AI-generated summaries
Home-page: https://github.com/mathiscode/ai-kernel-explorer
License: MIT
Author: mathiscode
Author-email: code@mathis.network
Requires-Python: >=3.10,<4.0
Classifier: Environment :: Console
Classifier: Intended Audience :: Developers
Classifier: Intended Audience :: System Administrators
Classifier: License :: OSI Approved :: MIT License
Classifier: Operating System :: POSIX :: Linux
Classifier: Programming Language :: Python :: 3
Classifier: Programming Language :: Python :: 3.10
Classifier: Programming Language :: Python :: 3.11
Classifier: Programming Language :: Python :: 3.12
Classifier: Topic :: Documentation
Classifier: Topic :: Software Development :: Documentation
Classifier: Topic :: System :: Operating System Kernels
Classifier: Topic :: Utilities
Requires-Dist: openai (>=1.38.0,<2.0.0)
Requires-Dist: textual (>=0.75.1,<0.76.0)
Requires-Dist: toml (>=0.10.2,<0.11.0)
Project-URL: Repository, https://github.com/mathiscode/ai-kernel-explorer
